odoo/addons/sale_customer_rank/README.rst
odoo/addons/sale_customer_rank/__init__.py
odoo/addons/sale_customer_rank/__manifest__.py
odoo/addons/sale_customer_rank/i18n/sale_customer_rank.pot
odoo/addons/sale_customer_rank/models/__init__.py
odoo/addons/sale_customer_rank/models/sale_order.py
odoo/addons/sale_customer_rank/readme/CONTRIBUTORS.rst
odoo/addons/sale_customer_rank/readme/DESCRIPTION.rst
odoo/addons/sale_customer_rank/static/description/icon.png
odoo/addons/sale_customer_rank/static/description/index.html
odoo13_addon_sale_customer_rank-13.0.1.0.1.dev3.dist-info/METADATA
odoo13_addon_sale_customer_rank-13.0.1.0.1.dev3.dist-info/WHEEL
odoo13_addon_sale_customer_rank-13.0.1.0.1.dev3.dist-info/top_level.txt
odoo13_addon_sale_customer_rank-13.0.1.0.1.dev3.dist-info/RECORD
